LICENSE
MANIFEST.in
README.md
setup.cfg
setup.py
Pokie_mail.egg-info/PKG-INFO
Pokie_mail.egg-info/SOURCES.txt
Pokie_mail.egg-info/dependency_links.txt
Pokie_mail.egg-info/not-zip-safe
Pokie_mail.egg-info/requires.txt
Pokie_mail.egg-info/top_level.txt
pokie_mail/__init__.py
pokie_mail/config.py
pokie_mail/constants.py
pokie_mail/helpers.py
pokie_mail/module.py
pokie_mail/cli/__init__.py
pokie_mail/cli/queue.py
pokie_mail/dto/__init__.py
pokie_mail/dto/records.py
pokie_mail/job/__init__.py
pokie_mail/job/queue.py
pokie_mail/repository/__init__.py
pokie_mail/repository/repositories.py
pokie_mail/service/__init__.py
pokie_mail/service/queue.py
pokie_mail/service/template.py
pokie_mail/sql/001-mail.sql
tests/__init__.py
tests/conftest.py
tests/test_builder.py
tests/service/__init__.py
tests/service/test_queue.py
tests/service/test_template.py
tests/unit/__init__.py
tests/unit/constants.py
tests/unit/fixtures.py