Metadata-Version: 2.4
Name: Pokie-mail
Version: 1.1.2
Summary: Transactional email module for Pokie
Home-page: https://git.oddbit.org/OddBit/pokie-mail
Author: João Pinheiro
License: BSD-3-Clause
Project-URL: Source, https://git.oddbit.org/OddBit/pokie-mail/
Classifier: Environment :: Web Environment
Classifier: Development Status :: 4 - Beta
Classifier: Intended Audience :: Developers
Classifier: License :: OSI Approved :: BSD License
Classifier: Operating System :: OS Independent
Classifier: Programming Language :: Python
Classifier: Programming Language :: Python :: 3.10
Classifier: Programming Language :: Python :: 3.11
Classifier: Programming Language :: Python :: 3.12
Classifier: Programming Language :: Python :: 3.13
Classifier: Programming Language :: Python :: 3.14
Classifier: Topic :: Internet :: WWW/HTTP
Classifier: Topic :: Internet :: WWW/HTTP :: Dynamic Content
Classifier: Topic :: Internet :: WWW/HTTP :: WSGI
Classifier: Topic :: Software Development :: Libraries :: Application Frameworks
Classifier: Topic :: Software Development :: Libraries :: Python Modules
Requires-Python: >=3.10
License-File: LICENSE
Requires-Dist: rick-db>=2.0.2
Requires-Dist: rick>=0.8.0
Requires-Dist: pokie>=0.9.2
Requires-Dist: rick-mailer>=1.1.1
Requires-Dist: setuptools
Requires-Dist: tabulate>=0.9.0
Dynamic: license-file
